fsglue/__init__.py
fsglue/client.py
fsglue/exceptions.py
fsglue/model.py
fsglue/property.py
fsglue-1.2.0.dist-info/LICENSE
fsglue-1.2.0.dist-info/METADATA
fsglue-1.2.0.dist-info/WHEEL
fsglue-1.2.0.dist-info/top_level.txt
fsglue-1.2.0.dist-info/RECORD
