Metadata-Version: 2.1
Name: fsglue
Version: 1.2.0
Summary: cloud firestore orm inspired by ndb
Home-page: https://github.com/g0e/fsglue
Author: g0e
Author-email: osogoe@g0e.net
License: MIT
Platform: UNKNOWN
License-File: LICENSE
Requires-Dist: google-cloud-firestore
Requires-Dist: jsonschema
